CHANGELOG.txt
LICENSE
MANIFEST.in
README.md
README.txt
setup.py
improvedinputs/__init__.py
improvedinputs/functions.py
improvedinputs.egg-info/PKG-INFO
improvedinputs.egg-info/SOURCES.txt
improvedinputs.egg-info/dependency_links.txt
improvedinputs.egg-info/top_level.txt
venv/Lib/site-packages/ptr.py
venv/Lib/site-packages/six.py
venv/Lib/site-packages/zipp.py
venv/Lib/site-packages/Pygments-2.11.2.dist-info/entry_points.txt
venv/Lib/site-packages/Pygments-2.11.2.dist-info/top_level.txt
venv/Lib/site-packages/_distutils_hack/__init__.py
venv/Lib/site-packages/_distutils_hack/override.py
venv/Lib/site-packages/_pytest/__init__.py
venv/Lib/site-packages/_pytest/_argcomplete.py
venv/Lib/site-packages/_pytest/_version.py
venv/Lib/site-packages/_pytest/cacheprovider.py
venv/Lib/site-packages/_pytest/capture.py
venv/Lib/site-packages/_pytest/compat.py
venv/Lib/site-packages/_pytest/debugging.py
venv/Lib/site-packages/_pytest/deprecated.py
venv/Lib/site-packages/_pytest/doctest.py
venv/Lib/site-packages/_pytest/faulthandler.py
venv/Lib/site-packages/_pytest/fixtures.py
venv/Lib/site-packages/_pytest/freeze_support.py
venv/Lib/site-packages/_pytest/helpconfig.py
venv/Lib/site-packages/_pytest/hookspec.py
venv/Lib/site-packages/_pytest/junitxml.py
venv/Lib/site-packages/_pytest/logging.py
venv/Lib/site-packages/_pytest/main.py
venv/Lib/site-packages/_pytest/monkeypatch.py
venv/Lib/site-packages/_pytest/nodes.py
venv/Lib/site-packages/_pytest/nose.py
venv/Lib/site-packages/_pytest/outcomes.py
venv/Lib/site-packages/_pytest/pastebin.py
venv/Lib/site-packages/_pytest/pathlib.py
venv/Lib/site-packages/_pytest/pytester.py
venv/Lib/site-packages/_pytest/pytester_assertions.py
venv/Lib/site-packages/_pytest/python.py
venv/Lib/site-packages/_pytest/python_api.py
venv/Lib/site-packages/_pytest/recwarn.py
venv/Lib/site-packages/_pytest/reports.py
venv/Lib/site-packages/_pytest/runner.py
venv/Lib/site-packages/_pytest/setuponly.py
venv/Lib/site-packages/_pytest/setupplan.py
venv/Lib/site-packages/_pytest/skipping.py
venv/Lib/site-packages/_pytest/stepwise.py
venv/Lib/site-packages/_pytest/store.py
venv/Lib/site-packages/_pytest/terminal.py
venv/Lib/site-packages/_pytest/threadexception.py
venv/Lib/site-packages/_pytest/timing.py
venv/Lib/site-packages/atomicwrites-1.4.0.dist-info/top_level.txt
venv/Lib/site-packages/attrs-21.4.0.dist-info/top_level.txt
venv/Lib/site-packages/bleach-4.1.0.dist-info/top_level.txt
venv/Lib/site-packages/bleach/_vendor/html5lib-1.1.dist-info/top_level.txt
venv/Lib/site-packages/certifi-2021.10.8.dist-info/top_level.txt
venv/Lib/site-packages/charset_normalizer-2.0.10.dist-info/entry_points.txt
venv/Lib/site-packages/charset_normalizer-2.0.10.dist-info/top_level.txt
venv/Lib/site-packages/colorama-0.4.4.dist-info/LICENSE.txt
venv/Lib/site-packages/colorama-0.4.4.dist-info/top_level.txt
venv/Lib/site-packages/docutils-0.18.1.dist-info/COPYING.txt
venv/Lib/site-packages/docutils-0.18.1.dist-info/top_level.txt
venv/Lib/site-packages/idna-3.3.dist-info/LICENSE.md
venv/Lib/site-packages/idna-3.3.dist-info/top_level.txt
venv/Lib/site-packages/importlib_metadata-4.10.1.dist-info/top_level.txt
venv/Lib/site-packages/iniconfig-1.1.1.dist-info/top_level.txt
venv/Lib/site-packages/keyring-23.5.0.dist-info/entry_points.txt
venv/Lib/site-packages/keyring-23.5.0.dist-info/top_level.txt
venv/Lib/site-packages/packaging-21.3.dist-info/top_level.txt
venv/Lib/site-packages/pip-21.3.1.dist-info/LICENSE.txt
venv/Lib/site-packages/pip-21.3.1.dist-info/entry_points.txt
venv/Lib/site-packages/pip-21.3.1.dist-info/top_level.txt
venv/Lib/site-packages/pkginfo-1.8.2.dist-info/LICENSE.txt
venv/Lib/site-packages/pkginfo-1.8.2.dist-info/entry_points.txt
venv/Lib/site-packages/pkginfo-1.8.2.dist-info/top_level.txt
venv/Lib/site-packages/pluggy-1.0.0.dist-info/top_level.txt
venv/Lib/site-packages/py-1.11.0.dist-info/top_level.txt
venv/Lib/site-packages/py/_vendored_packages/apipkg-2.0.0.dist-info/top_level.txt
venv/Lib/site-packages/py/_vendored_packages/iniconfig-1.1.1.dist-info/top_level.txt
venv/Lib/site-packages/pyparsing-3.0.6.dist-info/top_level.txt
venv/Lib/site-packages/pytest-6.2.5.dist-info/entry_points.txt
venv/Lib/site-packages/pytest-6.2.5.dist-info/top_level.txt
venv/Lib/site-packages/pytest_runner-5.3.1.dist-info/entry_points.txt
venv/Lib/site-packages/pytest_runner-5.3.1.dist-info/top_level.txt
venv/Lib/site-packages/pywin32_ctypes-0.2.0.dist-info/LICENSE.txt
venv/Lib/site-packages/pywin32_ctypes-0.2.0.dist-info/top_level.txt
venv/Lib/site-packages/readme_renderer-32.0.dist-info/entry_points.txt
venv/Lib/site-packages/readme_renderer-32.0.dist-info/top_level.txt
venv/Lib/site-packages/requests-2.27.1.dist-info/top_level.txt
venv/Lib/site-packages/requests_toolbelt-0.9.1.dist-info/top_level.txt
venv/Lib/site-packages/rfc3986-2.0.0.dist-info/top_level.txt
venv/Lib/site-packages/setuptools-58.1.0.dist-info/entry_points.txt
venv/Lib/site-packages/setuptools-58.1.0.dist-info/top_level.txt
venv/Lib/site-packages/six-1.16.0.dist-info/top_level.txt
venv/Lib/site-packages/toml-0.10.2.dist-info/top_level.txt
venv/Lib/site-packages/tqdm-4.62.3.dist-info/entry_points.txt
venv/Lib/site-packages/tqdm-4.62.3.dist-info/top_level.txt
venv/Lib/site-packages/twine-3.7.1.dist-info/entry_points.txt
venv/Lib/site-packages/twine-3.7.1.dist-info/top_level.txt
venv/Lib/site-packages/urllib3-1.26.8.dist-info/LICENSE.txt
venv/Lib/site-packages/urllib3-1.26.8.dist-info/top_level.txt
venv/Lib/site-packages/webencodings-0.5.1.dist-info/top_level.txt
venv/Lib/site-packages/wheel-0.37.1.dist-info/LICENSE.txt
venv/Lib/site-packages/wheel-0.37.1.dist-info/entry_points.txt
venv/Lib/site-packages/wheel-0.37.1.dist-info/top_level.txt
venv/Lib/site-packages/zipp-3.7.0.dist-info/top_level.txt
