Metadata-Version: 2.1
Name: improvedinputs
Version: 0.0.2
Summary: Improved inputs for your next project
Home-page: UNKNOWN
Author: Yigdo
Author-email: yigitgulay11@outlook.com
License: MIT
Keywords: input
Platform: UNKNOWN
Classifier: Development Status :: 5 - Production/Stable
Classifier: Intended Audience :: Education
Classifier: Operating System :: Microsoft :: Windows :: Windows 10
Classifier: License :: OSI Approved :: MIT License
Classifier: Programming Language :: Python :: 3
License-File: LICENSE
